daisy_dtb/__init__.py
daisy_dtb/book/__init__.py
daisy_dtb/book/daisybook.py
daisy_dtb/cache/__init__.py
daisy_dtb/cache/cache.py
daisy_dtb/cache/cachestats.py
daisy_dtb/models/__init__.py
daisy_dtb/models/audio.py
daisy_dtb/models/metadata.py
daisy_dtb/models/reference.py
daisy_dtb/models/section.py
daisy_dtb/models/smil.py
daisy_dtb/models/text.py
daisy_dtb/models/toc_entry.py
daisy_dtb/navigators/__init__.py
daisy_dtb/navigators/base_navigator.py
daisy_dtb/navigators/book_navigator.py
daisy_dtb/navigators/clip_navigator.py
daisy_dtb/navigators/section_navigator.py
daisy_dtb/navigators/toc_navigator.py
daisy_dtb/sources/__init__.py
daisy_dtb/sources/folder_source.py
daisy_dtb/sources/source.py
daisy_dtb/sources/zip_source.py
daisy_dtb/utilities/__init__.py
daisy_dtb/utilities/domlib.py
daisy_dtb/utilities/fetcher.py
daisy_dtb/utilities/logconfig.py
daisy_dtb-0.0.17.dist-info/METADATA
daisy_dtb-0.0.17.dist-info/WHEEL
daisy_dtb-0.0.17.dist-info/top_level.txt
daisy_dtb-0.0.17.dist-info/RECORD
