Metadata-Version: 2.2
Name: daisy-dtb
Version: 0.0.17
Summary: A library to deal with Daisy 2.02 digital talking books
Author-email: Martin Mohnhaupt <m.mohnhaupt@bluewin.ch>
Maintainer-email: Martin Mohnhaupt <m.mohnhaupt@bluewin.ch>
License: MIT License
Project-URL: Homepage, https://github.com/nicedata/daisy-dtb
Project-URL: Issues, https://github.com/nicedata/daisy-dtb/issues
Classifier: Development Status :: 3 - Alpha
Classifier: Programming Language :: Python :: 3.12
Requires-Python: >=3.11
Requires-Dist: chardet>=5.2.0
Requires-Dist: loguru>=0.7.3
